pyaare/__init__.py
pyaare/pyaare.py
test/__init__.py
test/aaretest.py
pyaare-1.4.0.dist-info/LICENSE
pyaare-1.4.0.dist-info/METADATA
pyaare-1.4.0.dist-info/WHEEL
pyaare-1.4.0.dist-info/top_level.txt
pyaare-1.4.0.dist-info/RECORD
