Metadata-Version: 2.1
Name: pyaare
Version: 1.4.0
Summary: A Python wrapper around the aare.guru API
Home-page: https://github.com/eliabieri/pyaare
Author: Elia Bieri
Author-email: bieri.elia@gmail.com
License: UNKNOWN
Platform: UNKNOWN
Classifier: Development Status :: 4 - Beta
Classifier: Intended Audience :: Developers
Classifier: Topic :: Internet
Classifier: License :: OSI Approved :: MIT License
Classifier: Programming Language :: Python :: 3.7
Classifier: Programming Language :: Python :: 3.8
Requires-Python: >=3.7
Requires-Dist: requests
